stea/__init__.py
stea/stea_client.py
stea/stea_config.py
stea/stea_input.py
stea/stea_keys.py
stea/stea_project.py
stea/stea_request.py
stea/stea_result.py
stea/version.py
fmu_steaclient-0.7.6.dist-info/LICENSE
fmu_steaclient-0.7.6.dist-info/METADATA
fmu_steaclient-0.7.6.dist-info/WHEEL
fmu_steaclient-0.7.6.dist-info/top_level.txt
fmu_steaclient-0.7.6.dist-info/RECORD
