Metadata-Version: 2.1
Name: fmu-steaclient
Version: 0.7.6
Summary: stea - calculate economic analysis
Home-page: https://github.com/equinor/fmu-steaclient
Author: Scout, Equinor ASA
Platform: any
Classifier: Development Status :: 1 - Planning
Classifier: Environment :: Plugins
Classifier: Intended Audience :: Developers
Classifier: Intended Audience :: Science/Research
Classifier: License :: OSI Approved :: GNU Lesser General Public License v3 or later (LGPLv3+)
Classifier: Natural Language :: English
Classifier: Programming Language :: Python
Classifier: Programming Language :: Python :: 3.8
Classifier: Programming Language :: Python :: 3.9
Classifier: Programming Language :: Python :: 3.10
Classifier: Topic :: Scientific/Engineering
Classifier: Topic :: Software Development :: Libraries :: Python Modules
License-File: LICENSE
Requires-Dist: requests
Requires-Dist: pyyaml
Requires-Dist: configsuite >=0.6
Requires-Dist: resdata
